reptaskorg/__init__.py
reptaskorg/reptaskorg.py
reptaskorg/test.py
reptaskorg-1.0.1.dist-info/LICENSE.txt
reptaskorg-1.0.1.dist-info/METADATA
reptaskorg-1.0.1.dist-info/WHEEL
reptaskorg-1.0.1.dist-info/top_level.txt
reptaskorg-1.0.1.dist-info/RECORD
