Metadata-Version: 2.1
Name: reptaskorg
Version: 1.0.1
Summary: Libary for repeated execution of functions at specific times.
Home-page: https://github.com/CeKl/reptaskorg
Author: Cedric Klimt
Author-email: cekl@gmx.net
License: MIT
Keywords: python,execute functions repeatedly
Platform: UNKNOWN
Classifier: License :: OSI Approved :: MIT License
Classifier: Intended Audience :: Developers
Classifier: Programming Language :: Python :: 3
Classifier: Operating System :: OS Independent
